{
    "$schema": "https://www.flowlauncher.com/schemas/plugin.schema.json",
    "ID": "badecafe-8037-1965-2026-a04b12c09d10",
    "ActionKeyword": "click",
    "Name": "FlClicker",
    "Description": "provides efficient TaskList Management for ClickUp.com",
    "Author": "realB12",
    "Version": "0.0.5",
    "Language": "csharp",
    "Website": "https://github.com/realB12/Flow.Launcher.Plugin.FlClicker",
    "IcoPath": "Images\\app.png",
    "ExecuteFileName": "Flow.Launcher.Plugin.FlClicker.dll"
}